./.gitignore
./PKG-INFO
./README.md
./pyproject.toml
./vision_agents/plugins/turbopuffer/__init__.py
./vision_agents/plugins/turbopuffer/turbopuffer_rag.py
vision_agents_plugins_turbopuffer-0.2.10.dist-info/METADATA
vision_agents_plugins_turbopuffer-0.2.10.dist-info/WHEEL
vision_agents_plugins_turbopuffer-0.2.10.dist-info/RECORD
