Metadata-Version: 2.4
Name: vision-agents-plugins-turbopuffer
Version: 0.2.10
Summary: TurboPuffer RAG integration for Vision Agents with hybrid search
Project-URL: Documentation, https://visionagents.ai/
Project-URL: Website, https://visionagents.ai/
Project-URL: Source, https://github.com/GetStream/Vision-Agents
License-Expression: MIT
Keywords: AI,RAG,agents,hybrid-search,turbopuffer,vector-search,voice agents
Requires-Python: >=3.10
Requires-Dist: langchain-google-genai>=2.1.4
Requires-Dist: langchain-text-splitters>=0.3.8
Requires-Dist: turbopuffer>=0.3.3
Requires-Dist: vision-agents
